task3/counter.sv
module counter #(
  parameter WIDTH = 8
)(
  // interface signals
  input  logic             clk,      // clock 
  input  logic             rst,      // reset 
  input  logic             ld,       // load counter from data
  input  logic [WIDTH-1:0] v,        // value to preload
  output logic [WIDTH-1:0] count     // count output
);

always_ff @ (posedge clk)
  if (rst) count <= {WIDTH{1'b0}};
  //else     count <= ld ? count + {{WIDTH-1{1'b0}},1'b1} : v; (step 1)
  else count <= ld ? count + {{WIDTH-1{1'b0}},1'b1} : count; //step 2

endmodule

task3/counter 2.vcd
$version Generated by VerilatedVcd $end
$date Fri Oct 28 21:23:51 2022 $end
$timescale 1ps $end

 $scope module TOP $end
  $var wire  1 # clk $end
  $var wire  8 ' count [7:0] $end
  $var wire  1 % ld $end
  $var wire  1 $ rst $end
  $var wire  8 & v [7:0] $end
  $scope module counter $end
   $var wire 32 ( WIDTH [31:0] $end
   $var wire  1 # clk $end
   $var wire  8 ' count [7:0] $end
   $var wire  1 % ld $end
   $var wire  1 $ rst $end
   $var wire  8 & v [7:0] $end
  $upscope $end
 $upscope $end
$enddefinitions $end


#0
1#
0$
0%
b00000000 &
b00000000 '
b00000000000000000000000000001000 (
#1
0#
#2
1#
b00110101 &
#3
0#
#4
1#
#5
0#
#6
1#
#7
0#
#8
1#
#9
0#
#10
1#
#11
0#
#12
1#
#13
0#
#14
1#
#15
0#
#16
1#
#17
0#
#18
1#
#19
0#
#20
1#
#21
0#
#22
1#
#23
0#
#24
1#
#25
0#
#26
1#
1%
#27
0#
#28
1#
0%
b00000001 '
#29
0#
#30
1#
#31
0#
#32
1#
#33
0#
#34
1#
#35
0#
#36
1#
#37
0#
#38
1#
#39
0#
#40
1#
#41
0#
#42
1#
#43
0#
#44
1#
#45
0#
#46
1#
#47
0#
#48
1#
1%
#49
0#
#50
1#
0%
b00000010 '
#51
0#
#52
1#
#53
0#
#54
1#
#55
0#
#56
1#
#57
0#
#58
1#
#59
0#
#60
1#
#61
0#
#62
1#
#63
0#
#64
1#
1%
#65
0#
#66
1#
0%
b00000011 '
#67
0#
#68
1#
#69
0#
#70
1#
#71
0#
#72
1#
#73
0#
#74
1#
#75
0#
#76
1#
#77
0#
#78
1#
#79
0#
#80
1#
1%
#81
0#
#82
1#
0%
b00000100 '
#83
0#
#84
1#
#85
0#
#86
1#
#87
0#
#88
1#
#89
0#
#90
1#
#91
0#
#92
1#
#93
0#
#94
1#
#95
0#
#96
1#
#97
0#
#98
1#
#99
0#
#100
1#
#101
0#
#102
1#
1%
#103
0#
#104
1#
0%
b00000101 '
